{
  "$schema": "https://mintlify.com/docs.json",
  "name": "Weiroll",
  "theme": "aspen",
  "colors": {
    "primary": "#6366F1",
    "light": "#818CF8",
    "dark": "#4F46E5"
  },
  "navbar": {
    "primary": {
      "type": "github",
      "href": "https://github.com/cowdao-grants/weiroll"
    }
  },
  "footer": {
    "socials": {
      "github": "https://github.com/cowdao-grants/weiroll"
    }
  },
  "navigation": {
    "tabs": [
      {
        "tab": "Documentation",
        "groups": [
          {
            "group": "Get Started",
            "pages": [
              "introduction",
              "installation",
              "quickstart"
            ]
          },
          {
            "group": "Core Concepts",
            "pages": [
              "concepts/understanding-weiroll",
              "concepts/how-it-works",
              "concepts/security-model"
            ]
          },
          {
            "group": "Guides",
            "pages": [
              "guides/integration",
              "guides/deployment",
              "guides/multi-chain"
            ]
          },
          {
            "group": "Development",
            "pages": [
              "development/building",
              "development/testing",
              "development/contributing"
            ]
          }
        ]
      },
      {
        "tab": "API Reference",
        "groups": [
          {
            "group": "Contract Reference",
            "pages": [
              "api/deployable-vm",
              "api/execute-function"
            ]
          },
          {
            "group": "Deployment Addresses",
            "pages": [
              "api/networks"
            ]
          }
        ]
      }
    ]
  }
}
